<?xml version = '1.0' encoding = 'UTF-8'?>
<Diagram class="oracle.dbtools.crest.swingui.datatypes.DPVDataTypes" id="C805065A-948D-ACC8-FD73-16A588EFDF11">
<createdBy>georgiydemo</createdBy>
<modifiedBy>georgiydemo</modifiedBy>
<createdTime>2020-10-15 09:27:34 UTC</createdTime>
<autoRoute>false</autoRoute>
<boxInbox>true</boxInbox>
<showLegend>false</showLegend>
<showLabels>true</showLabels>
<showRelAttributes>false</showRelAttributes>
<gridEnabled>false</gridEnabled>
<showGrid>false</showGrid>
<diagramColor>-1</diagramColor>
<display>false</display>
<notation>1</notation>
<objectViews>
<OView class="oracle.dbtools.crest.swingui.datatypes.TVStructuredType" oid="47E390DE-0671-C4B1-8428-0F45CBEE18F8" otype="StructuredType" vid="E3A854AD-C552-F46B-03EA-32B9A87E32D9">
<hideElementsInCurrentOnly>false</hideElementsInCurrentOnly>
<bounds x="20" y="20" width="100" height="100"/>
</OView>
<OView class="oracle.dbtools.crest.swingui.datatypes.TVStructuredType" oid="F72C39E0-D1CA-8821-2AD7-A1E95A37D3D1" otype="StructuredType" vid="D70FA113-A2B3-3145-6A37-FF5711A11222">
<hideElementsInCurrentOnly>false</hideElementsInCurrentOnly>
<bounds x="20" y="20" width="100" height="100"/>
</OView>
</objectViews>
</Diagram>